MANIFEST.in
README.md
VERSION
requirements.txt
setup.py
docs/source/conf.py
examples/django-application.py
examples/intro.py
ioc/__init__.py
ioc/apps.py
ioc/collection.py
ioc/dependency.py
ioc/etc.py
ioc/exc.py
ioc/fixtures.py
ioc/injector.py
ioc/loader.py
ioc/package.json
ioc/pkg.py
ioc/provider.py
ioc/requirement.py
ioc/utils.py
ioc/schema/__init__.py
ioc/schema/adapters.py
ioc/schema/base.py
ioc/schema/dependency.py
ioc/schema/exc.py
ioc/schema/iresolvable.py
ioc/schema/parser.py
ioc/schema/requirement.py
ioc/schema/resolver.py
ioc/schema/tests/test_unit_append.py
ioc/schema/tests/test_unit_argumentdependency_adapter.py
ioc/schema/tests/test_unit_callabledependency_adapter.py
ioc/schema/tests/test_unit_file_adapter.py
ioc/schema/tests/test_unit_literal_adapter.py
ioc/schema/tests/test_unit_nesteddependency_adapter.py
ioc/schema/tests/test_unit_requirement.py
ioc/schema/tests/test_unit_resolver.py
ioc/schema/tests/test_unit_schema.py
ioc/schema/tests/test_unit_schema_parser.py
ioc/schema/tests/test_unit_schema_requirement.py
ioc/schema/tests/test_unit_symbol_adapter.py
ioc/tests/__init__.py
ioc/tests/test_integration_collection.py
ioc/tests/test_integration_default.py
ioc/tests/test_integration_django.py
ioc/tests/test_integration_injector.py
ioc/tests/test_integration_ioc.py
ioc/tests/test_integration_load.py
ioc/tests/test_integration_override.py
ioc/tests/test_integration_regressions.py
ioc/tests/test_integration_unsatisfied_dependencies.py
ioc/tests/test_unit_async_inject.py
ioc/tests/test_unit_loader.py
ioc/tests/test_unit_provider.py
ioc/tests/test_unit_requirement.py
ioc/tests/test_unit_tagging.py
ioc/tests/test_unit_tags.py
ioc/tests/test_unit_utils_is_valid_identifier.py
ioc/tests/test_unit_variables.py
ioc/tests/examples/__init__.py
ioc/tests/examples/test_sqlalchemy.py
python_ioc.egg-info/PKG-INFO
python_ioc.egg-info/SOURCES.txt
python_ioc.egg-info/dependency_links.txt
python_ioc.egg-info/entry_points.txt
python_ioc.egg-info/requires.txt
python_ioc.egg-info/top_level.txt